thlink_backend_deployment/__init__.py
thlink_backend_deployment/app_lambda_layer.py
thlink_backend_deployment/resource_naming.py
thlink_backend_deployment-0.6.1.dist-info/LICENSE
thlink_backend_deployment-0.6.1.dist-info/WHEEL
thlink_backend_deployment-0.6.1.dist-info/METADATA
thlink_backend_deployment-0.6.1.dist-info/RECORD
