Metadata-Version: 2.1
Name: thlink-backend-deployment
Version: 0.6.1
Summary: 
Author: thlink
Requires-Python: >=3.7,<4.0
Classifier: Programming Language :: Python :: 3
Classifier: Programming Language :: Python :: 3.7
Classifier: Programming Language :: Python :: 3.8
Classifier: Programming Language :: Python :: 3.9
Requires-Dist: aws-cdk.aws-lambda (>=1.105.0,<2.0.0)
Requires-Dist: aws-cdk.core (>=1.105.0,<2.0.0)
